cando/__init__.py
cando/cando.py
cando_py-2.3.4.dist-info/licenses/AUTHORS.md
cando_py-2.3.4.dist-info/licenses/LICENSE.md
cando_py-2.3.4.dist-info/METADATA
cando_py-2.3.4.dist-info/WHEEL
cando_py-2.3.4.dist-info/top_level.txt
cando_py-2.3.4.dist-info/RECORD
