Metadata-Version: 2.4
Name: cando-py
Version: 2.3.4
Summary: CANDO is a unique computational drug discovery, design, and repurposing platform.
License: Copyright 2019 William Mangione
Project-URL: Homepage, http://compbio.buffalo.edu/protinfo/cando/
Keywords: drug discovery,drug design,translational bioinformatics,drug repurposing,computational biology,biomedical informatics,modeling and simulation,machine learning
Classifier: Development Status :: 5 - Production/Stable
Classifier: Intended Audience :: Science/Research
Classifier: Intended Audience :: Healthcare Industry
Classifier: Intended Audience :: Information Technology
Classifier: License :: OSI Approved :: BSD License
Classifier: Operating System :: POSIX :: Linux
Classifier: Operating System :: MacOS :: MacOS X
Classifier: Operating System :: Microsoft :: Windows :: Windows 10
Classifier: Programming Language :: Python :: 3
Classifier: Programming Language :: Python :: 3.7
Classifier: Programming Language :: Python :: 3.8
Classifier: Programming Language :: Python :: 3.9
Classifier: Programming Language :: Python :: 3.10
Requires-Python: <3.12,>=3.7
License-File: LICENSE.md
License-File: AUTHORS.md
Requires-Dist: requests>=2.28.1
Requires-Dist: matplotlib>=3.5.2
Requires-Dist: numpy>=1.21.6
Requires-Dist: pandas<2.2,>=1.3.5
Requires-Dist: rdkit>=2022.3.4
Requires-Dist: scikit-learn>=1.0.2
Requires-Dist: scipy>=1.7.3
Requires-Dist: tqdm
Requires-Dist: polars<0.20.10,>0.20.5
Requires-Dist: sqlalchemy==1.4.45
Requires-Dist: connectorx
Requires-Dist: pyarrow
Dynamic: license-file
